pawlib/__init__.py
pawlib/ai/__init__.py
pawlib/ai/embed/__init__.py
pawlib/ai/embed/embed_builder.py
pawlib/ai/rerank/__init__.py
pawlib/ai/rerank/rerank_manager.py
pawlib/ai/rerank/algorithm/__init__.py
pawlib/ai/rerank/algorithm/bce_rerank.py
pawlib/ai/rerank/entity/__init__.py
pawlib/ai/rerank/entity/rerank_config.py
pawlib/ai/summarize/__init__.py
pawlib/ai/summarize/summarize_manager.py
pawlib/ai/summarize/textrank/__init__.py
pawlib/ai/summarize/textrank/segmentation.py
pawlib/ai/summarize/textrank/stopwords.txt
pawlib/ai/summarize/textrank/textrank_keyword.py
pawlib/ai/summarize/textrank/textrank_sentence.py
pawlib/ai/summarize/textrank/util.py
pawlib/ai/utils/__init__.py
pawlib/ai/utils/gpu_utils.py
pawlib-0.0.0.post13.dist-info/METADATA
pawlib-0.0.0.post13.dist-info/WHEEL
pawlib-0.0.0.post13.dist-info/licenses/LICENSE
pawlib-0.0.0.post13.dist-info/RECORD
