Metadata-Version: 2.4
Name: pawlib
Version: 0.0.0.post13
Summary: Add your description here
License-File: LICENSE
Requires-Python: >=3.10
Requires-Dist: diskcache==5.6.3
Requires-Dist: falkordb==1.2.0
Requires-Dist: jieba>=0.42.1
Requires-Dist: jinja2==3.1.4
Requires-Dist: loguru>=0.7.0
Requires-Dist: nanoid==2.0.0
Requires-Dist: pandas==2.2.2
Requires-Dist: pillow==10.3.0
Requires-Dist: psycopg-binary==3.2.3
Requires-Dist: pyarmor==9.1.5
Requires-Dist: python-dotenv==1.1.0
Requires-Dist: redis==5.0.1
Requires-Dist: tqdm==4.66.4
Provides-Extra: aiops
Requires-Dist: mlflow==3.3.2; extra == 'aiops'
Provides-Extra: all
Requires-Dist: ansible-runner==2.4.1; extra == 'all'
Requires-Dist: ansible==10.7.0; extra == 'all'
Requires-Dist: azure-cognitiveservices-vision-computervision==0.9.0; extra == 'all'
Requires-Dist: duckduckgo-search==7.2.1; extra == 'all'
Requires-Dist: graphiti-core==0.20.4; extra == 'all'
Requires-Dist: jpype1==1.5.2; extra == 'all'
Requires-Dist: json-repair==0.39.1; extra == 'all'
Requires-Dist: kubernetes==32.0.1; extra == 'all'
Requires-Dist: langchain-community==0.3.27; extra == 'all'
Requires-Dist: langchain-experimental==0.3.4; extra == 'all'
Requires-Dist: langchain-huggingface==0.1.2; extra == 'all'
Requires-Dist: langchain-mcp-adapters==0.1.9; extra == 'all'
Requires-Dist: langchain-openai==0.3.28; extra == 'all'
Requires-Dist: langchain-postgres==0.0.15; extra == 'all'
Requires-Dist: langchain==0.3.27; extra == 'all'
Requires-Dist: langgraph==0.6.2; extra == 'all'
Requires-Dist: markdownify==0.12.1; extra == 'all'
Requires-Dist: mlflow==3.3.2; extra == 'all'
Requires-Dist: openpyxl==3.1.5; extra == 'all'
Requires-Dist: paddleclas==2.5.2; extra == 'all'
Requires-Dist: paddleocr==2.10.0; extra == 'all'
Requires-Dist: paddlepaddle==3.0.0; extra == 'all'
Requires-Dist: playwright==1.51.0; extra == 'all'
Requires-Dist: pymupdf==1.24.5; extra == 'all'
Requires-Dist: pytest-asyncio==0.26.0; extra == 'all'
Requires-Dist: pytest-cov==6.1.1; extra == 'all'
Requires-Dist: pytest-dotenv==0.5.2; extra == 'all'
Requires-Dist: pytest-html==4.1.1; extra == 'all'
Requires-Dist: pytest-sugar==1.0.0; extra == 'all'
Requires-Dist: pytest-xdist==3.6.1; extra == 'all'
Requires-Dist: pytest==8.3.5; extra == 'all'
Requires-Dist: python-docx==1.1.2; extra == 'all'
Requires-Dist: python-jenkins==1.8.2; extra == 'all'
Requires-Dist: python-pptx==0.6.23; extra == 'all'
Requires-Dist: sanic-ext==23.12.0; extra == 'all'
Requires-Dist: sanic-httpauth==0.2.0; extra == 'all'
Requires-Dist: sanic-testing==24.6.0; extra == 'all'
Requires-Dist: sanic==25.3.0; extra == 'all'
Requires-Dist: tabula-py==2.10.0; extra == 'all'
Requires-Dist: tabulate==0.9.0; extra == 'all'
Provides-Extra: containers
Requires-Dist: kubernetes==32.0.1; extra == 'containers'
Provides-Extra: devops
Requires-Dist: ansible-runner==2.4.1; extra == 'devops'
Requires-Dist: ansible==10.7.0; extra == 'devops'
Requires-Dist: python-jenkins==1.8.2; extra == 'devops'
Provides-Extra: document
Requires-Dist: jpype1==1.5.2; extra == 'document'
Requires-Dist: markdownify==0.12.1; extra == 'document'
Requires-Dist: openpyxl==3.1.5; extra == 'document'
Requires-Dist: pymupdf==1.24.5; extra == 'document'
Requires-Dist: python-docx==1.1.2; extra == 'document'
Requires-Dist: python-pptx==0.6.23; extra == 'document'
Requires-Dist: tabula-py==2.10.0; extra == 'document'
Requires-Dist: tabulate==0.9.0; extra == 'document'
Provides-Extra: llm
Requires-Dist: duckduckgo-search==7.2.1; extra == 'llm'
Requires-Dist: graphiti-core==0.20.4; extra == 'llm'
Requires-Dist: json-repair==0.39.1; extra == 'llm'
Requires-Dist: langchain-community==0.3.27; extra == 'llm'
Requires-Dist: langchain-experimental==0.3.4; extra == 'llm'
Requires-Dist: langchain-huggingface==0.1.2; extra == 'llm'
Requires-Dist: langchain-mcp-adapters==0.1.9; extra == 'llm'
Requires-Dist: langchain-openai==0.3.28; extra == 'llm'
Requires-Dist: langchain-postgres==0.0.15; extra == 'llm'
Requires-Dist: langchain==0.3.27; extra == 'llm'
Requires-Dist: langgraph==0.6.2; extra == 'llm'
Requires-Dist: playwright==1.51.0; extra == 'llm'
Provides-Extra: ocr
Requires-Dist: azure-cognitiveservices-vision-computervision==0.9.0; extra == 'ocr'
Requires-Dist: paddleclas==2.5.2; extra == 'ocr'
Requires-Dist: paddleocr==2.10.0; extra == 'ocr'
Requires-Dist: paddlepaddle==3.0.0; extra == 'ocr'
Provides-Extra: sanic
Requires-Dist: sanic-ext==23.12.0; extra == 'sanic'
Requires-Dist: sanic-httpauth==0.2.0; extra == 'sanic'
Requires-Dist: sanic==25.3.0; extra == 'sanic'
Provides-Extra: test
Requires-Dist: pytest-asyncio==0.26.0; extra == 'test'
Requires-Dist: pytest-cov==6.1.1; extra == 'test'
Requires-Dist: pytest-dotenv==0.5.2; extra == 'test'
Requires-Dist: pytest-html==4.1.1; extra == 'test'
Requires-Dist: pytest-sugar==1.0.0; extra == 'test'
Requires-Dist: pytest-xdist==3.6.1; extra == 'test'
Requires-Dist: pytest==8.3.5; extra == 'test'
Requires-Dist: sanic-testing==24.6.0; extra == 'test'
